{
  "_type": "export",
  "__export_format": 4,
  "__export_date": "2024-10-16T20:43:39.968Z",
  "__export_source": "insomnia.desktop.app:v2023.5.8",
  "resources": [
    {
      "_id": "req_99d6372ceb75405aa11f88004b07b2f1",
      "parentId": "fld_0a191757567e40a7b5e513ea2fee459b",
      "modified": 1728943532636,
      "created": 1728942551007,
      "url": "http://localhost:3000/production/",
      "name": "all productions",
      "description": "",
      "method": "GET",
      "body": {},
      "parameters": [
        {
          "id": "pair_4e50ff54e17d4eb7936a4f3adb772c9b",
          "name": "orderBy",
          "value": "id",
          "description": "",
          "disabled": false
        }
      ],
      "headers": [{ "name": "User-Agent", "value": "insomnia/2023.5.8" }],
      "authentication": {},
      "metaSortKey": -1727374137617,
      "isPrivate": false,
      "settingStoreCookies": true,
      "settingSendCookies": true,
      "settingDisableRenderRequestBody": false,
      "settingEncodeUrl": true,
      "settingRebuildPath": true,
      "settingFollowRedirects": "global",
      "_type": "request"
    },
    {
      "_id": "fld_0a191757567e40a7b5e513ea2fee459b",
      "parentId": "wrk_4b01b1ef345b4e99b769c016507fff36",
      "modified": 1728942551001,
      "created": 1728942551001,
      "name": "PRODUCTION",
      "description": "",
      "environment": {},
      "environmentPropertyOrder": null,
      "metaSortKey": -1727374083779.5,
      "_type": "request_group"
    },
    {
      "_id": "wrk_4b01b1ef345b4e99b769c016507fff36",
      "parentId": null,
      "modified": 1726460010541,
      "created": 1726460010541,
      "name": "CP-Planta Test App",
      "description": "",
      "scope": "collection",
      "_type": "workspace"
    },
    {
      "_id": "req_51137fc001414da181364341fce00e07",
      "parentId": "fld_0a191757567e40a7b5e513ea2fee459b",
      "modified": 1729009161324,
      "created": 1728942551016,
      "url": "http://localhost:3000/production/1",
      "name": "by id",
      "description": "",
      "method": "GET",
      "body": {},
      "parameters": [
        {
          "id": "pair_3ed6f8f5ae8348a4b7b3a9edb1754eac",
          "name": "",
          "value": "",
          "description": ""
        }
      ],
      "headers": [{ "name": "User-Agent", "value": "insomnia/2023.5.8" }],
      "authentication": {},
      "metaSortKey": -1727374137567,
      "isPrivate": false,
      "settingStoreCookies": true,
      "settingSendCookies": true,
      "settingDisableRenderRequestBody": false,
      "settingEncodeUrl": true,
      "settingRebuildPath": true,
      "settingFollowRedirects": "global",
      "_type": "request"
    },
    {
      "_id": "req_c37440cb20894049adfdd02fa171184f",
      "parentId": "fld_0a191757567e40a7b5e513ea2fee459b",
      "modified": 1729003733064,
      "created": 1728942551039,
      "url": "http://localhost:3000/production/",
      "name": "create new register",
      "description": "",
      "method": "POST",
      "body": {
        "mimeType": "application/json",
        "text": "{\n  \"number\": 1004,\n  \"description\": \"Produção de Mandioca\",\n  \"production_date\": \"2024-12-31T00:00:00Z\",\n  \"Production_Status\": \"CREATED\",\n  \"production_items\": [\n    {\n      \"final_product_id\": 10,\n      \"prodution_quantity_estimated\": 1000,\n      \"production_quantity_real\": 950,\n      \"lote\": \"LoteTY123\",\n      \"lote_expiration\": \"2024-12-31T00:00:00Z\"\n    },\n    {\n      \"final_product_id\": 11,\n      \"prodution_quantity_estimated\": 500,\n      \"production_quantity_real\": 450,\n      \"lote\": \"LoteTY456\",\n      \"lote_expiration\": \"2025-01-31T00:00:00Z\"\n    }\n  ]\n}"
      },
      "parameters": [],
      "headers": [
        { "name": "Content-Type", "value": "application/json" },
        { "name": "User-Agent", "value": "insomnia/2023.5.8" }
      ],
      "authentication": {},
      "metaSortKey": -1727374137467,
      "isPrivate": false,
      "settingStoreCookies": true,
      "settingSendCookies": true,
      "settingDisableRenderRequestBody": false,
      "settingEncodeUrl": true,
      "settingRebuildPath": true,
      "settingFollowRedirects": "global",
      "_type": "request"
    },
    {
      "_id": "req_915e3ab7197f4cfb9b9fcf53b6908bd4",
      "parentId": "fld_0a191757567e40a7b5e513ea2fee459b",
      "modified": 1729011919382,
      "created": 1729009053029,
      "url": "http://localhost:3000/production/1",
      "name": "update register",
      "description": "",
      "method": "PATCH",
      "body": {
        "mimeType": "application/json",
        "text": "{\n  \"number\": 1,\n  \"description\": \"Produção INTERNACIONAL\",\n  \"production_date\": \"2024-12-31T00:00:00Z\",\n  \"Production_Status\": \"SCHEDULED\",\n  \"production_items\": [\n    {\n      \"final_product_id\": 7,\n      \"prodution_quantity_estimated\": 1000,\n      \"production_quantity_real\": 950,\n      \"lote\": \"LoteTY123\",\n      \"lote_expiration\": \"2024-12-31T00:00:00Z\"\n    },\n    {\n      \"final_product_id\": 8,\n      \"prodution_quantity_estimated\": 500,\n      \"production_quantity_real\": 450,\n      \"lote\": \"LoteTY456\",\n      \"lote_expiration\": \"2025-01-31T00:00:00Z\"\n    }\n  ]\n}"
      },
      "parameters": [],
      "headers": [
        { "name": "Content-Type", "value": "application/json" },
        { "name": "User-Agent", "value": "insomnia/2023.5.8" }
      ],
      "authentication": {},
      "metaSortKey": -1727374137460.75,
      "isPrivate": false,
      "settingStoreCookies": true,
      "settingSendCookies": true,
      "settingDisableRenderRequestBody": false,
      "settingEncodeUrl": true,
      "settingRebuildPath": true,
      "settingFollowRedirects": "global",
      "_type": "request"
    },
    {
      "_id": "req_95360a03eefc40459d1ab4742ef5ad09",
      "parentId": "fld_46c78abd86b0447581dcc5356097d80f",
      "modified": 1728929247560,
      "created": 1728067605626,
      "url": "http://localhost:3000/production-order-steps/",
      "name": "all registers",
      "description": "",
      "method": "GET",
      "body": {},
      "parameters": [
        {
          "id": "pair_1aa222606f4244c89bf79f4346ff7e64",
          "name": "orderBy",
          "value": "id",
          "description": ""
        }
      ],
      "headers": [{ "name": "User-Agent", "value": "insomnia/2023.5.8" }],
      "authentication": {},
      "metaSortKey": -1727374149432,
      "isPrivate": false,
      "settingStoreCookies": true,
      "settingSendCookies": true,
      "settingDisableRenderRequestBody": false,
      "settingEncodeUrl": true,
      "settingRebuildPath": true,
      "settingFollowRedirects": "global",
      "_type": "request"
    },
    {
      "_id": "fld_46c78abd86b0447581dcc5356097d80f",
      "parentId": "wrk_4b01b1ef345b4e99b769c016507fff36",
      "modified": 1729050292598,
      "created": 1728067605616,
      "name": "PRODUCTION-ORDER-STEPS",
      "description": "",
      "environment": {},
      "environmentPropertyOrder": null,
      "metaSortKey": -1727374083773.25,
      "_type": "request_group"
    },
    {
      "_id": "req_918778205f7247cfb2d2f872c1688441",
      "parentId": "fld_46c78abd86b0447581dcc5356097d80f",
      "modified": 1728930395199,
      "created": 1728067605634,
      "url": "http://localhost:3000/production-order-steps/3",
      "name": "prod order steps by id",
      "description": "",
      "method": "GET",
      "body": {},
      "parameters": [],
      "headers": [{ "name": "User-Agent", "value": "insomnia/2023.5.8" }],
      "authentication": {},
      "metaSortKey": -1727374149382,
      "isPrivate": false,
      "settingStoreCookies": true,
      "settingSendCookies": true,
      "settingDisableRenderRequestBody": false,
      "settingEncodeUrl": true,
      "settingRebuildPath": true,
      "settingFollowRedirects": "global",
      "_type": "request"
    },
    {
      "_id": "req_1021214fc4d7443e98f58745158cc68e",
      "parentId": "fld_46c78abd86b0447581dcc5356097d80f",
      "modified": 1728930471146,
      "created": 1728067605620,
      "url": "http://localhost:3000/production-order-steps/3",
      "name": "update prod order steps",
      "description": "",
      "method": "PATCH",
      "body": { "mimeType": "application/json", "text": "" },
      "parameters": [
        {
          "id": "pair_4efb578c6a3c439dad6d7753294bedde",
          "name": "description",
          "value": "nova descrição da etapa",
          "description": "",
          "disabled": false
        }
      ],
      "headers": [
        { "name": "Content-Type", "value": "application/json" },
        { "name": "User-Agent", "value": "insomnia/2023.5.8" }
      ],
      "authentication": {},
      "metaSortKey": -1727374149357,
      "isPrivate": false,
      "settingStoreCookies": true,
      "settingSendCookies": true,
      "settingDisableRenderRequestBody": false,
      "settingEncodeUrl": true,
      "settingRebuildPath": true,
      "settingFollowRedirects": "global",
      "_type": "request"
    },
    {
      "_id": "req_1741348d8ee64010a51f962036663d99",
      "parentId": "fld_46c78abd86b0447581dcc5356097d80f",
      "modified": 1728930312003,
      "created": 1728067605646,
      "url": "http://localhost:3000/production-order-steps/",
      "name": "create prod order step",
      "description": "",
      "method": "POST",
      "body": {
        "mimeType": "application/json",
        "text": "\t{\n\t\t\"description\": \"Nova Etapa cadastrada\"\n\t}"
      },
      "parameters": [],
      "headers": [
        { "name": "Content-Type", "value": "application/json" },
        { "name": "User-Agent", "value": "insomnia/2023.5.8" }
      ],
      "authentication": {},
      "metaSortKey": -1727374149344.5,
      "isPrivate": false,
      "settingStoreCookies": true,
      "settingSendCookies": true,
      "settingDisableRenderRequestBody": false,
      "settingEncodeUrl": true,
      "settingRebuildPath": true,
      "settingFollowRedirects": "global",
      "_type": "request"
    },
    {
      "_id": "req_feb66b6fc3f64e3785790eb419b548a7",
      "parentId": "fld_46c78abd86b0447581dcc5356097d80f",
      "modified": 1728931314001,
      "created": 1728067605640,
      "url": "http://localhost:3000/production-order-steps/2",
      "name": "delete product by id",
      "description": "",
      "method": "DELETE",
      "body": {},
      "parameters": [],
      "headers": [{ "name": "User-Agent", "value": "insomnia/2023.5.8" }],
      "authentication": {},
      "metaSortKey": -1727374149332,
      "isPrivate": false,
      "settingStoreCookies": true,
      "settingSendCookies": true,
      "settingDisableRenderRequestBody": false,
      "settingEncodeUrl": true,
      "settingRebuildPath": true,
      "settingFollowRedirects": "global",
      "_type": "request"
    },
    {
      "_id": "req_8c16621978be47009eb7b2bd42c079ce",
      "parentId": "fld_b0153a7e4e484b8b8df337b4569e3033",
      "modified": 1728716668904,
      "created": 1726460020954,
      "url": "http://localhost:3000/users/",
      "name": "all users",
      "description": "",
      "method": "GET",
      "body": {},
      "parameters": [
        {
          "id": "pair_4e50ff54e17d4eb7936a4f3adb772c9b",
          "name": "orderBy",
          "value": "created_at",
          "description": ""
        }
      ],
      "headers": [{ "name": "User-Agent", "value": "insomnia/2023.5.8" }],
      "authentication": {},
      "metaSortKey": -1727374137617,
      "isPrivate": false,
      "settingStoreCookies": true,
      "settingSendCookies": true,
      "settingDisableRenderRequestBody": false,
      "settingEncodeUrl": true,
      "settingRebuildPath": true,
      "settingFollowRedirects": "global",
      "_type": "request"
    },
    {
      "_id": "fld_b0153a7e4e484b8b8df337b4569e3033",
      "parentId": "wrk_4b01b1ef345b4e99b769c016507fff36",
      "modified": 1729053457185,
      "created": 1727374068536,
      "name": "USERS",
      "description": "",
      "environment": {},
      "environmentPropertyOrder": null,
      "metaSortKey": -1727374083771.6875,
      "_type": "request_group"
    },
    {
      "_id": "req_44025cc10e0e4d7ab20ee0cb861c6995",
      "parentId": "fld_b0153a7e4e484b8b8df337b4569e3033",
      "modified": 1728970473541,
      "created": 1726460647056,
      "url": "http://localhost:3000/users/1600",
      "name": "user by id",
      "description": "",
      "method": "GET",
      "body": {},
      "parameters": [],
      "headers": [{ "name": "User-Agent", "value": "insomnia/2023.5.8" }],
      "authentication": {},
      "metaSortKey": -1727374137567,
      "isPrivate": false,
      "settingStoreCookies": true,
      "settingSendCookies": true,
      "settingDisableRenderRequestBody": false,
      "settingEncodeUrl": true,
      "settingRebuildPath": true,
      "settingFollowRedirects": "global",
      "_type": "request"
    },
    {
      "_id": "req_4f999c91eb4446e29526de1ea58282a9",
      "parentId": "fld_b0153a7e4e484b8b8df337b4569e3033",
      "modified": 1728970483655,
      "created": 1728079518531,
      "url": "http://localhost:3000/users/",
      "name": "create user",
      "description": "",
      "method": "POST",
      "body": {
        "mimeType": "application/json",
        "text": "{\n\t\"email\": \"abigail@gmail.com\",\n\t\"password\": \"cpplanta\"\n}"
      },
      "parameters": [],
      "headers": [
        { "name": "Content-Type", "value": "application/json" },
        { "name": "User-Agent", "value": "insomnia/2023.5.8" }
      ],
      "authentication": {},
      "metaSortKey": -1727374137467,
      "isPrivate": false,
      "settingStoreCookies": true,
      "settingSendCookies": true,
      "settingDisableRenderRequestBody": false,
      "settingEncodeUrl": true,
      "settingRebuildPath": true,
      "settingFollowRedirects": "global",
      "_type": "request"
    },
    {
      "_id": "req_33e9ccd1832f46d7b548060d9d3751d1",
      "parentId": "fld_b0153a7e4e484b8b8df337b4569e3033",
      "modified": 1728970522866,
      "created": 1726460785901,
      "url": "http://localhost:3000/users/5",
      "name": "update user",
      "description": "",
      "method": "PATCH",
      "body": { "mimeType": "application/json", "text": "" },
      "parameters": [
        {
          "id": "pair_1f3e2e600c984bde9a4f93f5f6f4e85a",
          "name": "email",
          "value": "abigabiga@gmail.com",
          "description": ""
        },
        {
          "id": "pair_e019e2d8c8b44000885e037555c85fdf",
          "name": "password",
          "value": "abracadabra",
          "description": ""
        },
        {
          "id": "pair_f2347f84ea4442baa076556e0fd2cd82",
          "name": "role",
          "value": "DEFAULT",
          "description": ""
        },
        {
          "id": "pair_00f31d91221a48ce93acbbcd0f8e8c60",
          "name": "username",
          "value": "abigail",
          "description": ""
        },
        {
          "id": "pair_5daf7d6b34524f6c81e5045dacb35592",
          "name": "first_name",
          "value": "Abigail",
          "description": ""
        },
        {
          "id": "pair_5818026e787d4de784446a60ba2e8622",
          "name": "last_name",
          "value": "Silva",
          "description": ""
        },
        {
          "id": "pair_fce470409e0849c18e3348eef9b8fe07",
          "name": "gender",
          "value": "FEMALE",
          "description": ""
        }
      ],
      "headers": [
        { "name": "Content-Type", "value": "application/json" },
        { "name": "User-Agent", "value": "insomnia/2023.5.8" }
      ],
      "authentication": {},
      "metaSortKey": -1727374137454.5,
      "isPrivate": false,
      "settingStoreCookies": true,
      "settingSendCookies": true,
      "settingDisableRenderRequestBody": false,
      "settingEncodeUrl": true,
      "settingRebuildPath": true,
      "settingFollowRedirects": "global",
      "_type": "request"
    },
    {
      "_id": "req_370c78eb666e4ddf92a52c6c4606374f",
      "parentId": "fld_b0153a7e4e484b8b8df337b4569e3033",
      "modified": 1728970542536,
      "created": 1726460693045,
      "url": "http://localhost:3000/users/5",
      "name": "delete user by id",
      "description": "",
      "method": "DELETE",
      "body": {},
      "parameters": [],
      "headers": [{ "name": "User-Agent", "value": "insomnia/2023.5.8" }],
      "authentication": {},
      "metaSortKey": -1727374137442,
      "isPrivate": false,
      "settingStoreCookies": true,
      "settingSendCookies": true,
      "settingDisableRenderRequestBody": false,
      "settingEncodeUrl": true,
      "settingRebuildPath": true,
      "settingFollowRedirects": "global",
      "_type": "request"
    },
    {
      "_id": "req_02219dcced84450a96e3603c2d5a4f05",
      "parentId": "fld_b0153a7e4e484b8b8df337b4569e3033",
      "modified": 1728970562960,
      "created": 1728079545403,
      "url": "http://localhost:3000/users/activate/f",
      "name": "reactivate user",
      "description": "",
      "method": "POST",
      "body": { "mimeType": "application/json", "text": "" },
      "parameters": [],
      "headers": [
        { "name": "Content-Type", "value": "application/json" },
        { "name": "User-Agent", "value": "insomnia/2023.5.8" }
      ],
      "authentication": {},
      "metaSortKey": -1727374137429.5,
      "isPrivate": false,
      "settingStoreCookies": true,
      "settingSendCookies": true,
      "settingDisableRenderRequestBody": false,
      "settingEncodeUrl": true,
      "settingRebuildPath": true,
      "settingFollowRedirects": "global",
      "_type": "request"
    },
    {
      "_id": "req_773abad67c684b4ebfbf6c0d64e35e5e",
      "parentId": "fld_d8a90a51945a43c38dca61884044cdac",
      "modified": 1729050355258,
      "created": 1729050301953,
      "url": "http://localhost:3000/production-steps-progress/",
      "name": "all registers",
      "description": "",
      "method": "GET",
      "body": {},
      "parameters": [
        {
          "id": "pair_1aa222606f4244c89bf79f4346ff7e64",
          "name": "orderBy",
          "value": "id",
          "description": ""
        }
      ],
      "headers": [{ "name": "User-Agent", "value": "insomnia/2023.5.8" }],
      "authentication": {},
      "metaSortKey": -1727374149432,
      "isPrivate": false,
      "settingStoreCookies": true,
      "settingSendCookies": true,
      "settingDisableRenderRequestBody": false,
      "settingEncodeUrl": true,
      "settingRebuildPath": true,
      "settingFollowRedirects": "global",
      "_type": "request"
    },
    {
      "_id": "fld_d8a90a51945a43c38dca61884044cdac",
      "parentId": "wrk_4b01b1ef345b4e99b769c016507fff36",
      "modified": 1729050332406,
      "created": 1729050301941,
      "name": "PRODUCTION STEPS PROGRESS",
      "description": "",
      "environment": {},
      "environmentPropertyOrder": null,
      "metaSortKey": -1727374083770.125,
      "_type": "request_group"
    },
    {
      "_id": "req_0917b361fce645ad81eb8a5f4ac7c9b1",
      "parentId": "fld_d8a90a51945a43c38dca61884044cdac",
      "modified": 1729050415308,
      "created": 1729050301960,
      "url": "http://localhost:3000/production-steps-progress/1",
      "name": "prod order steps by id",
      "description": "",
      "method": "GET",
      "body": {},
      "parameters": [],
      "headers": [{ "name": "User-Agent", "value": "insomnia/2023.5.8" }],
      "authentication": {},
      "metaSortKey": -1727374149382,
      "isPrivate": false,
      "settingStoreCookies": true,
      "settingSendCookies": true,
      "settingDisableRenderRequestBody": false,
      "settingEncodeUrl": true,
      "settingRebuildPath": true,
      "settingFollowRedirects": "global",
      "_type": "request"
    },
    {
      "_id": "req_bdd5fcef9d5e48f89cfa7fcd749bd9b5",
      "parentId": "fld_d8a90a51945a43c38dca61884044cdac",
      "modified": 1729050301946,
      "created": 1729050301946,
      "url": "http://localhost:3000/production-order-steps/3",
      "name": "update prod order steps",
      "description": "",
      "method": "PATCH",
      "body": { "mimeType": "application/json", "text": "" },
      "parameters": [
        {
          "id": "pair_4efb578c6a3c439dad6d7753294bedde",
          "name": "description",
          "value": "nova descrição da etapa",
          "description": "",
          "disabled": false
        }
      ],
      "headers": [
        { "name": "Content-Type", "value": "application/json" },
        { "name": "User-Agent", "value": "insomnia/2023.5.8" }
      ],
      "authentication": {},
      "metaSortKey": -1727374149357,
      "isPrivate": false,
      "settingStoreCookies": true,
      "settingSendCookies": true,
      "settingDisableRenderRequestBody": false,
      "settingEncodeUrl": true,
      "settingRebuildPath": true,
      "settingFollowRedirects": "global",
      "_type": "request"
    },
    {
      "_id": "req_0e3ac0f75ac049219a87feda94981b9f",
      "parentId": "fld_d8a90a51945a43c38dca61884044cdac",
      "modified": 1729050301971,
      "created": 1729050301971,
      "url": "http://localhost:3000/production-order-steps/",
      "name": "create prod order step",
      "description": "",
      "method": "POST",
      "body": {
        "mimeType": "application/json",
        "text": "\t{\n\t\t\"description\": \"Nova Etapa cadastrada\"\n\t}"
      },
      "parameters": [],
      "headers": [
        { "name": "Content-Type", "value": "application/json" },
        { "name": "User-Agent", "value": "insomnia/2023.5.8" }
      ],
      "authentication": {},
      "metaSortKey": -1727374149344.5,
      "isPrivate": false,
      "settingStoreCookies": true,
      "settingSendCookies": true,
      "settingDisableRenderRequestBody": false,
      "settingEncodeUrl": true,
      "settingRebuildPath": true,
      "settingFollowRedirects": "global",
      "_type": "request"
    },
    {
      "_id": "req_09a293f6c83e4a76aaec76927b0ab53a",
      "parentId": "fld_d8a90a51945a43c38dca61884044cdac",
      "modified": 1729050459053,
      "created": 1729050301966,
      "url": "http://localhost:3000/production-steps-progress/1",
      "name": "delete product by id",
      "description": "",
      "method": "DELETE",
      "body": {},
      "parameters": [],
      "headers": [{ "name": "User-Agent", "value": "insomnia/2023.5.8" }],
      "authentication": {},
      "metaSortKey": -1727374149332,
      "isPrivate": false,
      "settingStoreCookies": true,
      "settingSendCookies": true,
      "settingDisableRenderRequestBody": false,
      "settingEncodeUrl": true,
      "settingRebuildPath": true,
      "settingFollowRedirects": "global",
      "_type": "request"
    },
    {
      "_id": "req_927df25f78e842efb3ccd3944bd5982d",
      "parentId": "fld_60390ffa61564118bf2b3de9a2dd9069",
      "modified": 1728081604071,
      "created": 1728066918738,
      "url": "http://localhost:3000/groups/",
      "name": "all groups",
      "description": "",
      "method": "GET",
      "body": {},
      "parameters": [
        {
          "id": "pair_1aa222606f4244c89bf79f4346ff7e64",
          "name": "orderBy",
          "value": "id",
          "description": "",
          "disabled": true
        }
      ],
      "headers": [{ "name": "User-Agent", "value": "insomnia/2023.5.8" }],
      "authentication": {},
      "metaSortKey": -1727374149632,
      "isPrivate": false,
      "settingStoreCookies": true,
      "settingSendCookies": true,
      "settingDisableRenderRequestBody": false,
      "settingEncodeUrl": true,
      "settingRebuildPath": true,
      "settingFollowRedirects": "global",
      "_type": "request"
    },
    {
      "_id": "fld_60390ffa61564118bf2b3de9a2dd9069",
      "parentId": "wrk_4b01b1ef345b4e99b769c016507fff36",
      "modified": 1728067016773,
      "created": 1728066918725,
      "name": "GROUPS",
      "description": "",
      "environment": {},
      "environmentPropertyOrder": null,
      "metaSortKey": -1727374083767,
      "_type": "request_group"
    },
    {
      "_id": "req_709e9da855964981b3d2642baf9a8b9a",
      "parentId": "fld_60390ffa61564118bf2b3de9a2dd9069",
      "modified": 1728107752489,
      "created": 1728066918745,
      "url": "http://localhost:3000/groups/1",
      "name": "group by id",
      "description": "",
      "method": "GET",
      "body": {},
      "parameters": [],
      "headers": [{ "name": "User-Agent", "value": "insomnia/2023.5.8" }],
      "authentication": {},
      "metaSortKey": -1727374149582,
      "isPrivate": false,
      "settingStoreCookies": true,
      "settingSendCookies": true,
      "settingDisableRenderRequestBody": false,
      "settingEncodeUrl": true,
      "settingRebuildPath": true,
      "settingFollowRedirects": "global",
      "_type": "request"
    },
    {
      "_id": "req_a73587f5606c42a6b90edca37e4a1b2c",
      "parentId": "fld_60390ffa61564118bf2b3de9a2dd9069",
      "modified": 1728133376369,
      "created": 1728066918759,
      "url": "http://localhost:3000/groups/",
      "name": "create group",
      "description": "",
      "method": "POST",
      "body": {
        "mimeType": "application/json",
        "text": "\t{\n\t\t\"description\": \"NOVO GRUPO CRIADO\"\n\t}"
      },
      "parameters": [],
      "headers": [
        { "name": "Content-Type", "value": "application/json" },
        { "name": "User-Agent", "value": "insomnia/2023.5.8" }
      ],
      "authentication": {},
      "metaSortKey": -1727374149532,
      "isPrivate": false,
      "settingStoreCookies": true,
      "settingSendCookies": true,
      "settingDisableRenderRequestBody": false,
      "settingEncodeUrl": true,
      "settingRebuildPath": true,
      "settingFollowRedirects": "global",
      "_type": "request"
    },
    {
      "_id": "req_5facda68217542eeb7ddadb5f73d821d",
      "parentId": "fld_60390ffa61564118bf2b3de9a2dd9069",
      "modified": 1728133406486,
      "created": 1728066918752,
      "url": "http://localhost:3000/groups/2",
      "name": "delete group by id",
      "description": "",
      "method": "DELETE",
      "body": {},
      "parameters": [],
      "headers": [{ "name": "User-Agent", "value": "insomnia/2023.5.8" }],
      "authentication": {},
      "metaSortKey": -1727374149332,
      "isPrivate": false,
      "settingStoreCookies": true,
      "settingSendCookies": true,
      "settingDisableRenderRequestBody": false,
      "settingEncodeUrl": true,
      "settingRebuildPath": true,
      "settingFollowRedirects": "global",
      "_type": "request"
    },
    {
      "_id": "req_3b6f3b02eb5b4d879e68723400893c98",
      "parentId": "fld_60390ffa61564118bf2b3de9a2dd9069",
      "modified": 1728133417121,
      "created": 1728066918765,
      "url": "http://localhost:3000/groups/activate/2",
      "name": "reactivate group by id",
      "description": "",
      "method": "POST",
      "body": {},
      "parameters": [],
      "headers": [{ "name": "User-Agent", "value": "insomnia/2023.5.8" }],
      "authentication": {},
      "metaSortKey": -1727374149282,
      "isPrivate": false,
      "settingStoreCookies": true,
      "settingSendCookies": true,
      "settingDisableRenderRequestBody": false,
      "settingEncodeUrl": true,
      "settingRebuildPath": true,
      "settingFollowRedirects": "global",
      "_type": "request"
    },
    {
      "_id": "req_c0a4f9f75ba941dd915bb2aa38abaeee",
      "parentId": "fld_60390ffa61564118bf2b3de9a2dd9069",
      "modified": 1728133435799,
      "created": 1728066918730,
      "url": "http://localhost:3000/groups/1",
      "name": "update group",
      "description": "",
      "method": "PATCH",
      "body": { "mimeType": "application/json", "text": "" },
      "parameters": [
        {
          "id": "pair_2b0c0be95b9746fe85515bcd96c9d726",
          "name": "description",
          "value": "CONSERVADORES",
          "description": ""
        }
      ],
      "headers": [
        { "name": "Content-Type", "value": "application/json" },
        { "name": "User-Agent", "value": "insomnia/2023.5.8" }
      ],
      "authentication": {},
      "metaSortKey": -1727374149232,
      "isPrivate": false,
      "settingStoreCookies": true,
      "settingSendCookies": true,
      "settingDisableRenderRequestBody": false,
      "settingEncodeUrl": true,
      "settingRebuildPath": true,
      "settingFollowRedirects": "global",
      "_type": "request"
    },
    {
      "_id": "req_7b4ac89ec74941db9a7db514ebcfe554",
      "parentId": "fld_cb2211c37f844a0e8aae9e0a2769982b",
      "modified": 1728576797018,
      "created": 1728576485932,
      "url": "http://localhost:3000/stock-locations/",
      "name": "all locations",
      "description": "",
      "method": "GET",
      "body": {},
      "parameters": [
        {
          "id": "pair_1aa222606f4244c89bf79f4346ff7e64",
          "name": "orderBy",
          "value": "id",
          "description": "",
          "disabled": true
        }
      ],
      "headers": [{ "name": "User-Agent", "value": "insomnia/2023.5.8" }],
      "authentication": {},
      "metaSortKey": -1727374149632,
      "isPrivate": false,
      "settingStoreCookies": true,
      "settingSendCookies": true,
      "settingDisableRenderRequestBody": false,
      "settingEncodeUrl": true,
      "settingRebuildPath": true,
      "settingFollowRedirects": "global",
      "_type": "request"
    },
    {
      "_id": "fld_cb2211c37f844a0e8aae9e0a2769982b",
      "parentId": "wrk_4b01b1ef345b4e99b769c016507fff36",
      "modified": 1728576485883,
      "created": 1728576485883,
      "name": "STOCK_LOCATIONS",
      "description": "",
      "environment": {},
      "environmentPropertyOrder": null,
      "metaSortKey": -1727374083763.875,
      "_type": "request_group"
    },
    {
      "_id": "req_66492f1cfaa5459ab7128bca280861c4",
      "parentId": "fld_cb2211c37f844a0e8aae9e0a2769982b",
      "modified": 1728623848811,
      "created": 1728576485940,
      "url": "http://localhost:3000/stock-locations/3",
      "name": "location by id",
      "description": "",
      "method": "GET",
      "body": {},
      "parameters": [],
      "headers": [{ "name": "User-Agent", "value": "insomnia/2023.5.8" }],
      "authentication": {},
      "metaSortKey": -1727374149582,
      "isPrivate": false,
      "settingStoreCookies": true,
      "settingSendCookies": true,
      "settingDisableRenderRequestBody": false,
      "settingEncodeUrl": true,
      "settingRebuildPath": true,
      "settingFollowRedirects": "global",
      "_type": "request"
    },
    {
      "_id": "req_4ccb3c559873468988079cfa56c2104f",
      "parentId": "fld_cb2211c37f844a0e8aae9e0a2769982b",
      "modified": 1728625541453,
      "created": 1728576485956,
      "url": "http://localhost:3000/stock-locations/",
      "name": "create stock-location",
      "description": "",
      "method": "POST",
      "body": {
        "mimeType": "application/json",
        "text": "\t{\n\t\t\"description\": \"CAMINHÃO FRIGORIFICO\"\n\t}"
      },
      "parameters": [],
      "headers": [
        { "name": "Content-Type", "value": "application/json" },
        { "name": "User-Agent", "value": "insomnia/2023.5.8" }
      ],
      "authentication": {},
      "metaSortKey": -1727374149532,
      "isPrivate": false,
      "settingStoreCookies": true,
      "settingSendCookies": true,
      "settingDisableRenderRequestBody": false,
      "settingEncodeUrl": true,
      "settingRebuildPath": true,
      "settingFollowRedirects": "global",
      "_type": "request"
    },
    {
      "_id": "req_174d9a26f15b4b339eee066603323bad",
      "parentId": "fld_cb2211c37f844a0e8aae9e0a2769982b",
      "modified": 1728624513014,
      "created": 1728576485948,
      "url": "http://localhost:3000/stock-locations/1",
      "name": "delete location by id",
      "description": "",
      "method": "DELETE",
      "body": {},
      "parameters": [],
      "headers": [{ "name": "User-Agent", "value": "insomnia/2023.5.8" }],
      "authentication": {},
      "metaSortKey": -1727374149332,
      "isPrivate": false,
      "settingStoreCookies": true,
      "settingSendCookies": true,
      "settingDisableRenderRequestBody": false,
      "settingEncodeUrl": true,
      "settingRebuildPath": true,
      "settingFollowRedirects": "global",
      "_type": "request"
    },
    {
      "_id": "req_d4008c44adef4ee99b3c446befe4a427",
      "parentId": "fld_cb2211c37f844a0e8aae9e0a2769982b",
      "modified": 1728624489211,
      "created": 1728576485964,
      "url": "http://localhost:3000/stock-locations/activate/1",
      "name": "reactivate location by id",
      "description": "",
      "method": "POST",
      "body": {},
      "parameters": [],
      "headers": [{ "name": "User-Agent", "value": "insomnia/2023.5.8" }],
      "authentication": {},
      "metaSortKey": -1727374149282,
      "isPrivate": false,
      "settingStoreCookies": true,
      "settingSendCookies": true,
      "settingDisableRenderRequestBody": false,
      "settingEncodeUrl": true,
      "settingRebuildPath": true,
      "settingFollowRedirects": "global",
      "_type": "request"
    },
    {
      "_id": "req_c55be2e5538948bc96ba284e7337bc2e",
      "parentId": "fld_cb2211c37f844a0e8aae9e0a2769982b",
      "modified": 1728626721601,
      "created": 1728576485902,
      "url": "http://localhost:3000/stock-locations/3",
      "name": "update stock-location",
      "description": "",
      "method": "PATCH",
      "body": { "mimeType": "application/json", "text": "" },
      "parameters": [
        {
          "id": "pair_2b0c0be95b9746fe85515bcd96c9d726",
          "name": "description",
          "value": "meu deposito favorito",
          "description": ""
        }
      ],
      "headers": [
        { "name": "Content-Type", "value": "application/json" },
        { "name": "User-Agent", "value": "insomnia/2023.5.8" }
      ],
      "authentication": {},
      "metaSortKey": -1727374149232,
      "isPrivate": false,
      "settingStoreCookies": true,
      "settingSendCookies": true,
      "settingDisableRenderRequestBody": false,
      "settingEncodeUrl": true,
      "settingRebuildPath": true,
      "settingFollowRedirects": "global",
      "_type": "request"
    },
    {
      "_id": "req_5c733c17675346f09738b480df4f241d",
      "parentId": "fld_e672d5f0e8be47b7ac9096f48e2e9e48",
      "modified": 1729095886100,
      "created": 1729053487736,
      "url": "http://localhost:3000/stock/",
      "name": "all stock",
      "description": "",
      "method": "GET",
      "body": {},
      "parameters": [
        {
          "id": "pair_1aa222606f4244c89bf79f4346ff7e64",
          "name": "orderBy",
          "value": "id",
          "description": "",
          "disabled": false
        }
      ],
      "headers": [{ "name": "User-Agent", "value": "insomnia/2023.5.8" }],
      "authentication": {},
      "metaSortKey": -1727374149632,
      "isPrivate": false,
      "settingStoreCookies": true,
      "settingSendCookies": true,
      "settingDisableRenderRequestBody": false,
      "settingEncodeUrl": true,
      "settingRebuildPath": true,
      "settingFollowRedirects": "global",
      "_type": "request"
    },
    {
      "_id": "fld_e672d5f0e8be47b7ac9096f48e2e9e48",
      "parentId": "wrk_4b01b1ef345b4e99b769c016507fff36",
      "modified": 1729053487723,
      "created": 1729053487723,
      "name": "STOCK",
      "description": "",
      "environment": {},
      "environmentPropertyOrder": null,
      "metaSortKey": -1727374083762.3125,
      "_type": "request_group"
    },
    {
      "_id": "req_5fc8480935c94c7bbd4b9a98bc8a40ab",
      "parentId": "fld_e672d5f0e8be47b7ac9096f48e2e9e48",
      "modified": 1729062437207,
      "created": 1729053487744,
      "url": "http://localhost:3000/stock/3",
      "name": "stock by arguments",
      "description": "",
      "method": "GET",
      "body": {},
      "parameters": [],
      "headers": [{ "name": "User-Agent", "value": "insomnia/2023.5.8" }],
      "authentication": {},
      "metaSortKey": -1727374149582,
      "isPrivate": false,
      "settingStoreCookies": true,
      "settingSendCookies": true,
      "settingDisableRenderRequestBody": false,
      "settingEncodeUrl": true,
      "settingRebuildPath": true,
      "settingFollowRedirects": "global",
      "_type": "request"
    },
    {
      "_id": "req_bc4ee370a2f14f14990ff0e114daf232",
      "parentId": "fld_e672d5f0e8be47b7ac9096f48e2e9e48",
      "modified": 1729111272635,
      "created": 1729053487760,
      "url": "http://localhost:3000/stock/",
      "name": "stock - insert register (input, output, others)",
      "description": "",
      "method": "POST",
      "body": {
        "mimeType": "application/json",
        "text": "{\n  \"document_number\": \"3017\",\n  \"document_date\": \"2024-09-15T10:30:00.000Z\",\n  \"stock_moviment\": \"INPUT\",\n  \"stock_items\": [\n    {\n      \"product_id\": 1,\n      \"lote\": \"LOTE-TESTE\",\n     \"expiration\": \"2025-01-15T00:00:00.000Z\",\n      \"quantity\": 200,\n      \"unit_price\": 10.5,\n      \"total_price\": 157.5,\n      \"supplier\": 10,\n      \"costumer\": 20,\n      \"observation\": \"Observação do item\",\n      \"image_link\": \"http://example.com/image.jpg\"\n    }\n  ]\n}\n"
      },
      "parameters": [],
      "headers": [
        { "name": "Content-Type", "value": "application/json" },
        { "name": "User-Agent", "value": "insomnia/2023.5.8" }
      ],
      "authentication": {},
      "metaSortKey": -1727374149532,
      "isPrivate": false,
      "settingStoreCookies": true,
      "settingSendCookies": true,
      "settingDisableRenderRequestBody": false,
      "settingEncodeUrl": true,
      "settingRebuildPath": true,
      "settingFollowRedirects": "global",
      "_type": "request"
    },
    {
      "_id": "req_93fce14a5d8d4fd1a09bf71ca826dfa2",
      "parentId": "fld_e672d5f0e8be47b7ac9096f48e2e9e48",
      "modified": 1729053757178,
      "created": 1729053487728,
      "url": "http://localhost:3000/stock-locations/3",
      "name": "stock - update register",
      "description": "",
      "method": "PATCH",
      "body": { "mimeType": "application/json", "text": "" },
      "parameters": [
        {
          "id": "pair_2b0c0be95b9746fe85515bcd96c9d726",
          "name": "description",
          "value": "meu deposito favorito",
          "description": ""
        }
      ],
      "headers": [
        { "name": "Content-Type", "value": "application/json" },
        { "name": "User-Agent", "value": "insomnia/2023.5.8" }
      ],
      "authentication": {},
      "metaSortKey": -1727374149432,
      "isPrivate": false,
      "settingStoreCookies": true,
      "settingSendCookies": true,
      "settingDisableRenderRequestBody": false,
      "settingEncodeUrl": true,
      "settingRebuildPath": true,
      "settingFollowRedirects": "global",
      "_type": "request"
    },
    {
      "_id": "req_0ccd438b4f1f4f2abec7f2d5ab306c5f",
      "parentId": "fld_e672d5f0e8be47b7ac9096f48e2e9e48",
      "modified": 1729097873745,
      "created": 1729053487752,
      "url": "http://localhost:3000/stock/1",
      "name": "stock - delete",
      "description": "",
      "method": "DELETE",
      "body": {},
      "parameters": [],
      "headers": [{ "name": "User-Agent", "value": "insomnia/2023.5.8" }],
      "authentication": {},
      "metaSortKey": -1727374149332,
      "isPrivate": false,
      "settingStoreCookies": true,
      "settingSendCookies": true,
      "settingDisableRenderRequestBody": false,
      "settingEncodeUrl": true,
      "settingRebuildPath": true,
      "settingFollowRedirects": "global",
      "_type": "request"
    },
    {
      "_id": "req_a2a0401d729e4bf4ba5f788377f48ef3",
      "parentId": "fld_9bf05157909049798bb8c128f0799505",
      "modified": 1728137454049,
      "created": 1728137426184,
      "url": "http://localhost:3000/persons/",
      "name": "all persons",
      "description": "",
      "method": "GET",
      "body": {},
      "parameters": [
        {
          "id": "pair_1aa222606f4244c89bf79f4346ff7e64",
          "name": "orderBy",
          "value": "id",
          "description": "",
          "disabled": true
        }
      ],
      "headers": [{ "name": "User-Agent", "value": "insomnia/2023.5.8" }],
      "authentication": {},
      "metaSortKey": -1727374149632,
      "isPrivate": false,
      "settingStoreCookies": true,
      "settingSendCookies": true,
      "settingDisableRenderRequestBody": false,
      "settingEncodeUrl": true,
      "settingRebuildPath": true,
      "settingFollowRedirects": "global",
      "_type": "request"
    },
    {
      "_id": "fld_9bf05157909049798bb8c128f0799505",
      "parentId": "wrk_4b01b1ef345b4e99b769c016507fff36",
      "modified": 1728137426076,
      "created": 1728137426076,
      "name": "PERSONS",
      "description": "",
      "environment": {},
      "environmentPropertyOrder": null,
      "metaSortKey": -1727374083760.75,
      "_type": "request_group"
    },
    {
      "_id": "req_37949da611064477b886ea9f5fef4fd2",
      "parentId": "fld_9bf05157909049798bb8c128f0799505",
      "modified": 1728138483618,
      "created": 1728137426196,
      "url": "http://localhost:3000/persons/2",
      "name": "person by id",
      "description": "",
      "method": "GET",
      "body": {},
      "parameters": [],
      "headers": [{ "name": "User-Agent", "value": "insomnia/2023.5.8" }],
      "authentication": {},
      "metaSortKey": -1727374149582,
      "isPrivate": false,
      "settingStoreCookies": true,
      "settingSendCookies": true,
      "settingDisableRenderRequestBody": false,
      "settingEncodeUrl": true,
      "settingRebuildPath": true,
      "settingFollowRedirects": "global",
      "_type": "request"
    },
    {
      "_id": "req_ff49539127904bf29a7dde078d9d9a3f",
      "parentId": "fld_9bf05157909049798bb8c128f0799505",
      "modified": 1728139250634,
      "created": 1728137426208,
      "url": "http://localhost:3000/persons/",
      "name": "create person",
      "description": "",
      "method": "POST",
      "body": {
        "mimeType": "application/json",
        "text": "\t{\n\t\t\"name\": \"Fruteira do Ifood\"\n\t}"
      },
      "parameters": [],
      "headers": [
        { "name": "Content-Type", "value": "application/json" },
        { "name": "User-Agent", "value": "insomnia/2023.5.8" }
      ],
      "authentication": {},
      "metaSortKey": -1727374149532,
      "isPrivate": false,
      "settingStoreCookies": true,
      "settingSendCookies": true,
      "settingDisableRenderRequestBody": false,
      "settingEncodeUrl": true,
      "settingRebuildPath": true,
      "settingFollowRedirects": "global",
      "_type": "request"
    },
    {
      "_id": "req_cb439e042d06414cb2abc0fcc8cc796e",
      "parentId": "fld_9bf05157909049798bb8c128f0799505",
      "modified": 1728138530405,
      "created": 1728137426203,
      "url": "http://localhost:3000/persons/1",
      "name": "delete person by id",
      "description": "",
      "method": "DELETE",
      "body": {},
      "parameters": [],
      "headers": [{ "name": "User-Agent", "value": "insomnia/2023.5.8" }],
      "authentication": {},
      "metaSortKey": -1727374149332,
      "isPrivate": false,
      "settingStoreCookies": true,
      "settingSendCookies": true,
      "settingDisableRenderRequestBody": false,
      "settingEncodeUrl": true,
      "settingRebuildPath": true,
      "settingFollowRedirects": "global",
      "_type": "request"
    },
    {
      "_id": "req_41c5444b022d4150b7155d6ac9a8bbf7",
      "parentId": "fld_9bf05157909049798bb8c128f0799505",
      "modified": 1728139268467,
      "created": 1728137426213,
      "url": "http://localhost:3000/persons/activate/1",
      "name": "reactivate person by id",
      "description": "",
      "method": "POST",
      "body": {},
      "parameters": [],
      "headers": [{ "name": "User-Agent", "value": "insomnia/2023.5.8" }],
      "authentication": {},
      "metaSortKey": -1727374149282,
      "isPrivate": false,
      "settingStoreCookies": true,
      "settingSendCookies": true,
      "settingDisableRenderRequestBody": false,
      "settingEncodeUrl": true,
      "settingRebuildPath": true,
      "settingFollowRedirects": "global",
      "_type": "request"
    },
    {
      "_id": "req_073dc82548ee4040b1d78297301a994f",
      "parentId": "fld_9bf05157909049798bb8c128f0799505",
      "modified": 1728139277987,
      "created": 1728137426127,
      "url": "http://localhost:3000/persons/5",
      "name": "update person",
      "description": "",
      "method": "PATCH",
      "body": { "mimeType": "application/json", "text": "" },
      "parameters": [
        {
          "id": "pair_2b0c0be95b9746fe85515bcd96c9d726",
          "name": "name",
          "value": "Atualizei nome da pessoa",
          "description": ""
        }
      ],
      "headers": [
        { "name": "Content-Type", "value": "application/json" },
        { "name": "User-Agent", "value": "insomnia/2023.5.8" }
      ],
      "authentication": {},
      "metaSortKey": -1727374149232,
      "isPrivate": false,
      "settingStoreCookies": true,
      "settingSendCookies": true,
      "settingDisableRenderRequestBody": false,
      "settingEncodeUrl": true,
      "settingRebuildPath": true,
      "settingFollowRedirects": "global",
      "_type": "request"
    },
    {
      "_id": "req_77e50679512b46cf851879b2043f5335",
      "parentId": "fld_a6256d64748f4e489002072d31e87e4c",
      "modified": 1728085605674,
      "created": 1728066935542,
      "url": "http://localhost:3000/categories/",
      "name": "all categories",
      "description": "",
      "method": "GET",
      "body": {},
      "parameters": [
        {
          "id": "pair_1aa222606f4244c89bf79f4346ff7e64",
          "name": "orderBy",
          "value": "id",
          "description": "",
          "disabled": true
        }
      ],
      "headers": [{ "name": "User-Agent", "value": "insomnia/2023.5.8" }],
      "authentication": {},
      "metaSortKey": -1727374149632,
      "isPrivate": false,
      "settingStoreCookies": true,
      "settingSendCookies": true,
      "settingDisableRenderRequestBody": false,
      "settingEncodeUrl": true,
      "settingRebuildPath": true,
      "settingFollowRedirects": "global",
      "_type": "request"
    },
    {
      "_id": "fld_a6256d64748f4e489002072d31e87e4c",
      "parentId": "wrk_4b01b1ef345b4e99b769c016507fff36",
      "modified": 1728067018913,
      "created": 1728066935529,
      "name": "CATEGORIES",
      "description": "",
      "environment": {},
      "environmentPropertyOrder": null,
      "metaSortKey": -1727374083754.5,
      "_type": "request_group"
    },
    {
      "_id": "req_142788abb7554d20806c6dc81082c9e2",
      "parentId": "fld_a6256d64748f4e489002072d31e87e4c",
      "modified": 1728101411875,
      "created": 1728066935547,
      "url": "http://localhost:3000/categories/3",
      "name": "categories by id",
      "description": "",
      "method": "GET",
      "body": {},
      "parameters": [],
      "headers": [{ "name": "User-Agent", "value": "insomnia/2023.5.8" }],
      "authentication": {},
      "metaSortKey": -1727374149582,
      "isPrivate": false,
      "settingStoreCookies": true,
      "settingSendCookies": true,
      "settingDisableRenderRequestBody": false,
      "settingEncodeUrl": true,
      "settingRebuildPath": true,
      "settingFollowRedirects": "global",
      "_type": "request"
    },
    {
      "_id": "req_a591830825b741fc829e52f26a7a5800",
      "parentId": "fld_a6256d64748f4e489002072d31e87e4c",
      "modified": 1728131448907,
      "created": 1728066935561,
      "url": "http://localhost:3000/categories/",
      "name": "create category",
      "description": "",
      "method": "POST",
      "body": {
        "mimeType": "application/json",
        "text": "{\n\t\"description\": \"DESCARTE\"\n}"
      },
      "parameters": [],
      "headers": [
        { "name": "Content-Type", "value": "application/json" },
        { "name": "User-Agent", "value": "insomnia/2023.5.8" }
      ],
      "authentication": {},
      "metaSortKey": -1727374149532,
      "isPrivate": false,
      "settingStoreCookies": true,
      "settingSendCookies": true,
      "settingDisableRenderRequestBody": false,
      "settingEncodeUrl": true,
      "settingRebuildPath": true,
      "settingFollowRedirects": "global",
      "_type": "request"
    },
    {
      "_id": "req_972b982cd0124dd690113b3ab2691ca6",
      "parentId": "fld_a6256d64748f4e489002072d31e87e4c",
      "modified": 1728131468980,
      "created": 1728066935532,
      "url": "http://localhost:3000/categories/3",
      "name": "update category",
      "description": "",
      "method": "PATCH",
      "body": { "mimeType": "application/json", "text": "" },
      "parameters": [
        {
          "id": "pair_2b0c0be95b9746fe85515bcd96c9d726",
          "name": "description",
          "value": "ALTEREI A DESCRIÇÃO",
          "description": ""
        }
      ],
      "headers": [
        { "name": "Content-Type", "value": "application/json" },
        { "name": "User-Agent", "value": "insomnia/2023.5.8" }
      ],
      "authentication": {},
      "metaSortKey": -1727374149482,
      "isPrivate": false,
      "settingStoreCookies": true,
      "settingSendCookies": true,
      "settingDisableRenderRequestBody": false,
      "settingEncodeUrl": true,
      "settingRebuildPath": true,
      "settingFollowRedirects": "global",
      "_type": "request"
    },
    {
      "_id": "req_7bf71bc1b8ad466095dc1d03ea5a4684",
      "parentId": "fld_a6256d64748f4e489002072d31e87e4c",
      "modified": 1728131499485,
      "created": 1728066935554,
      "url": "http://localhost:3000/categories/1600",
      "name": "delete category by id",
      "description": "",
      "method": "DELETE",
      "body": {},
      "parameters": [],
      "headers": [{ "name": "User-Agent", "value": "insomnia/2023.5.8" }],
      "authentication": {},
      "metaSortKey": -1727374149332,
      "isPrivate": false,
      "settingStoreCookies": true,
      "settingSendCookies": true,
      "settingDisableRenderRequestBody": false,
      "settingEncodeUrl": true,
      "settingRebuildPath": true,
      "settingFollowRedirects": "global",
      "_type": "request"
    },
    {
      "_id": "req_07e5f31f8efd4fcca41b61bfb3e0004b",
      "parentId": "fld_a6256d64748f4e489002072d31e87e4c",
      "modified": 1728131529950,
      "created": 1728066935567,
      "url": "http://localhost:3000/categories/activate/3",
      "name": "reactivate category by id",
      "description": "",
      "method": "POST",
      "body": {},
      "parameters": [],
      "headers": [{ "name": "User-Agent", "value": "insomnia/2023.5.8" }],
      "authentication": {},
      "metaSortKey": -1727374149232,
      "isPrivate": false,
      "settingStoreCookies": true,
      "settingSendCookies": true,
      "settingDisableRenderRequestBody": false,
      "settingEncodeUrl": true,
      "settingRebuildPath": true,
      "settingFollowRedirects": "global",
      "_type": "request"
    },
    {
      "_id": "req_031e2e09e0cb486c963b998dabb14ecb",
      "parentId": "fld_fa5f8975c45c4b1a8daf952c66e01776",
      "modified": 1728484953730,
      "created": 1726865914018,
      "url": "http://localhost:3000/products/",
      "name": "all products",
      "description": "",
      "method": "GET",
      "body": {},
      "parameters": [
        {
          "id": "pair_1aa222606f4244c89bf79f4346ff7e64",
          "name": "orderBy",
          "value": "sku",
          "description": ""
        }
      ],
      "headers": [{ "name": "User-Agent", "value": "insomnia/2023.5.8" }],
      "authentication": {},
      "metaSortKey": -1727374149432,
      "isPrivate": false,
      "settingStoreCookies": true,
      "settingSendCookies": true,
      "settingDisableRenderRequestBody": false,
      "settingEncodeUrl": true,
      "settingRebuildPath": true,
      "settingFollowRedirects": "global",
      "_type": "request"
    },
    {
      "_id": "fld_fa5f8975c45c4b1a8daf952c66e01776",
      "parentId": "wrk_4b01b1ef345b4e99b769c016507fff36",
      "modified": 1728066945653,
      "created": 1727374075227,
      "name": "PRODUCTS",
      "description": "",
      "environment": {},
      "environmentPropertyOrder": null,
      "metaSortKey": -1727374083742,
      "_type": "request_group"
    },
    {
      "_id": "req_98a8599bac2c425ab579cafc7074af7b",
      "parentId": "fld_fa5f8975c45c4b1a8daf952c66e01776",
      "modified": 1728484822238,
      "created": 1726865953903,
      "url": "http://localhost:3000/products/2",
      "name": "product by id",
      "description": "",
      "method": "GET",
      "body": {},
      "parameters": [],
      "headers": [{ "name": "User-Agent", "value": "insomnia/2023.5.8" }],
      "authentication": {},
      "metaSortKey": -1727374149382,
      "isPrivate": false,
      "settingStoreCookies": true,
      "settingSendCookies": true,
      "settingDisableRenderRequestBody": false,
      "settingEncodeUrl": true,
      "settingRebuildPath": true,
      "settingFollowRedirects": "global",
      "_type": "request"
    },
    {
      "_id": "req_6f4a8e200c2e4ed3a656d723e095895d",
      "parentId": "fld_fa5f8975c45c4b1a8daf952c66e01776",
      "modified": 1728361069828,
      "created": 1727234016888,
      "url": "http://localhost:3000/products/2",
      "name": "delete product by id",
      "description": "",
      "method": "DELETE",
      "body": {},
      "parameters": [],
      "headers": [{ "name": "User-Agent", "value": "insomnia/2023.5.8" }],
      "authentication": {},
      "metaSortKey": -1727374149332,
      "isPrivate": false,
      "settingStoreCookies": true,
      "settingSendCookies": true,
      "settingDisableRenderRequestBody": false,
      "settingEncodeUrl": true,
      "settingRebuildPath": true,
      "settingFollowRedirects": "global",
      "_type": "request"
    },
    {
      "_id": "req_63697addd15c4b6284ef83cf77ca9c91",
      "parentId": "fld_fa5f8975c45c4b1a8daf952c66e01776",
      "modified": 1728484841842,
      "created": 1727400914682,
      "url": "http://localhost:3000/products/activate/2",
      "name": "reactivate product by id",
      "description": "",
      "method": "POST",
      "body": {},
      "parameters": [],
      "headers": [{ "name": "User-Agent", "value": "insomnia/2023.5.8" }],
      "authentication": {},
      "metaSortKey": -1727374149282,
      "isPrivate": false,
      "settingStoreCookies": true,
      "settingSendCookies": true,
      "settingDisableRenderRequestBody": false,
      "settingEncodeUrl": true,
      "settingRebuildPath": true,
      "settingFollowRedirects": "global",
      "_type": "request"
    },
    {
      "_id": "req_54c20bd1a3c44a5997e86c7046d6b71c",
      "parentId": "fld_fa5f8975c45c4b1a8daf952c66e01776",
      "modified": 1728484894332,
      "created": 1726864797770,
      "url": "http://localhost:3000/products/1600",
      "name": "update product",
      "description": "",
      "method": "PATCH",
      "body": { "mimeType": "application/json", "text": "" },
      "parameters": [
        {
          "id": "pair_4efb578c6a3c439dad6d7753294bedde",
          "name": "origin",
          "value": "MADE",
          "description": "",
          "disabled": false
        },
        {
          "id": "pair_563ba9931c6e49fa9bad00603d41f28f",
          "name": "category_id",
          "value": "1",
          "description": "",
          "disabled": false
        },
        {
          "id": "pair_5380b02a4fbe46088a91d9fe5c54bd96",
          "name": "group_id",
          "value": "1",
          "description": "",
          "disabled": false
        },
        {
          "id": "pair_8ed01a5930a2467bae6080c496e84518",
          "name": "supplier_id",
          "value": "1",
          "description": "",
          "disabled": false
        },
        {
          "id": "pair_a7fa6ba98ff6419e9dad8655124feb51",
          "name": "nutritional_info",
          "value": "{\t\t\"fat\": {\t\t\t\"total\": 999,\t\t\t\"trans\": 999,\t\t\t\"saturated\": 999\t\t},\t\t\"sodium\": 999,\t\t\"protein\": 999,\t\t\"calories\": 999,\t\t\"vitamins\": {\t\t\t\"iron\": 999,\t\t\t\"calcium\": 999,\t\t\t\"vitamin_a\": 999,\t\t\t\"vitamin_c\": 999\t\t},\t\t\"carbohydrates\": {\t\t\t\"fiber\": 999,\t\t\t\"total\": 999,\t\t\t\"sugars\": 999\t\t}}",
          "description": "",
          "disabled": false
        },
        {
          "id": "pair_2b0c0be95b9746fe85515bcd96c9d726",
          "name": "description",
          "value": "mix de folhas verdes",
          "description": ""
        }
      ],
      "headers": [
        { "name": "Content-Type", "value": "application/json" },
        { "name": "User-Agent", "value": "insomnia/2023.5.8" }
      ],
      "authentication": {},
      "metaSortKey": -1727374149232,
      "isPrivate": false,
      "settingStoreCookies": true,
      "settingSendCookies": true,
      "settingDisableRenderRequestBody": false,
      "settingEncodeUrl": true,
      "settingRebuildPath": true,
      "settingFollowRedirects": "global",
      "_type": "request"
    },
    {
      "_id": "req_141417207d0c4579a0c10c7a1d8dfa75",
      "parentId": "fld_fa5f8975c45c4b1a8daf952c66e01776",
      "modified": 1728484917452,
      "created": 1727386317492,
      "url": "http://localhost:3000/products/",
      "name": "create product",
      "description": "",
      "method": "POST",
      "body": {
        "mimeType": "application/json",
        "text": "\t{\n\t\t\"description\": \"banana nanica\",\n\t\t\"code\": \"banana nanica\",\n\t\t\"sku\": \"banana nanica\",\n\t\t\"origin\": \"RAW_MATERIAL\",\n\t\t\"unit_measure\": \"UN\",\n\t\t\"category_id\": 4,\n\t\t\"group_id\": 4,\n\t\t\"supplier_id\": 4\n\t}"
      },
      "parameters": [],
      "headers": [
        { "name": "Content-Type", "value": "application/json" },
        { "name": "User-Agent", "value": "insomnia/2023.5.8" }
      ],
      "authentication": {},
      "metaSortKey": -1727374143374.5,
      "isPrivate": false,
      "settingStoreCookies": true,
      "settingSendCookies": true,
      "settingDisableRenderRequestBody": false,
      "settingEncodeUrl": true,
      "settingRebuildPath": true,
      "settingFollowRedirects": "global",
      "_type": "request"
    },
    {
      "_id": "req_fcfa1fe514644881b0fffe884c381cb1",
      "parentId": "fld_afca2dc23f124866a433f6675c7289ad",
      "modified": 1728929247560,
      "created": 1728067605626,
      "url": "http://localhost:3000/production-order-steps/",
      "name": "all registers",
      "description": "",
      "method": "GET",
      "body": {},
      "parameters": [
        {
          "id": "pair_1aa222606f4244c89bf79f4346ff7e64",
          "name": "orderBy",
          "value": "id",
          "description": ""
        }
      ],
      "headers": [{ "name": "User-Agent", "value": "insomnia/2023.5.8" }],
      "authentication": {},
      "metaSortKey": -1727374149432,
      "isPrivate": false,
      "settingStoreCookies": true,
      "settingSendCookies": true,
      "settingDisableRenderRequestBody": false,
      "settingEncodeUrl": true,
      "settingRebuildPath": true,
      "settingFollowRedirects": "global",
      "_type": "request"
    },
    {
      "_id": "fld_afca2dc23f124866a433f6675c7289ad",
      "parentId": "wrk_4b01b1ef345b4e99b769c016507fff36",
      "modified": 1728929277721,
      "created": 1728067605616,
      "name": "PRODUCTION-ORDER-STEPS",
      "description": "",
      "environment": {},
      "environmentPropertyOrder": null,
      "metaSortKey": -1725588557538.0684,
      "_type": "request_group"
    },
    {
      "_id": "req_2c5692c622594275a930312854fff0db",
      "parentId": "fld_afca2dc23f124866a433f6675c7289ad",
      "modified": 1728930395199,
      "created": 1728067605634,
      "url": "http://localhost:3000/production-order-steps/3",
      "name": "prod order steps by id",
      "description": "",
      "method": "GET",
      "body": {},
      "parameters": [],
      "headers": [{ "name": "User-Agent", "value": "insomnia/2023.5.8" }],
      "authentication": {},
      "metaSortKey": -1727374149382,
      "isPrivate": false,
      "settingStoreCookies": true,
      "settingSendCookies": true,
      "settingDisableRenderRequestBody": false,
      "settingEncodeUrl": true,
      "settingRebuildPath": true,
      "settingFollowRedirects": "global",
      "_type": "request"
    },
    {
      "_id": "req_a31359535f324c5886a955adbefbba1f",
      "parentId": "fld_afca2dc23f124866a433f6675c7289ad",
      "modified": 1728930471146,
      "created": 1728067605620,
      "url": "http://localhost:3000/production-order-steps/3",
      "name": "update prod order steps",
      "description": "",
      "method": "PATCH",
      "body": { "mimeType": "application/json", "text": "" },
      "parameters": [
        {
          "id": "pair_4efb578c6a3c439dad6d7753294bedde",
          "name": "description",
          "value": "nova descrição da etapa",
          "description": "",
          "disabled": false
        }
      ],
      "headers": [
        { "name": "Content-Type", "value": "application/json" },
        { "name": "User-Agent", "value": "insomnia/2023.5.8" }
      ],
      "authentication": {},
      "metaSortKey": -1727374149357,
      "isPrivate": false,
      "settingStoreCookies": true,
      "settingSendCookies": true,
      "settingDisableRenderRequestBody": false,
      "settingEncodeUrl": true,
      "settingRebuildPath": true,
      "settingFollowRedirects": "global",
      "_type": "request"
    },
    {
      "_id": "req_482c94b2e39b4519835725fb8499e0cc",
      "parentId": "fld_afca2dc23f124866a433f6675c7289ad",
      "modified": 1728930312003,
      "created": 1728067605646,
      "url": "http://localhost:3000/production-order-steps/",
      "name": "create prod order step",
      "description": "",
      "method": "POST",
      "body": {
        "mimeType": "application/json",
        "text": "\t{\n\t\t\"description\": \"Nova Etapa cadastrada\"\n\t}"
      },
      "parameters": [],
      "headers": [
        { "name": "Content-Type", "value": "application/json" },
        { "name": "User-Agent", "value": "insomnia/2023.5.8" }
      ],
      "authentication": {},
      "metaSortKey": -1727374149344.5,
      "isPrivate": false,
      "settingStoreCookies": true,
      "settingSendCookies": true,
      "settingDisableRenderRequestBody": false,
      "settingEncodeUrl": true,
      "settingRebuildPath": true,
      "settingFollowRedirects": "global",
      "_type": "request"
    },
    {
      "_id": "req_861919404c3e4d2a986414d33927b0df",
      "parentId": "fld_afca2dc23f124866a433f6675c7289ad",
      "modified": 1728931314001,
      "created": 1728067605640,
      "url": "http://localhost:3000/production-order-steps/2",
      "name": "delete product by id",
      "description": "",
      "method": "DELETE",
      "body": {},
      "parameters": [],
      "headers": [{ "name": "User-Agent", "value": "insomnia/2023.5.8" }],
      "authentication": {},
      "metaSortKey": -1727374149332,
      "isPrivate": false,
      "settingStoreCookies": true,
      "settingSendCookies": true,
      "settingDisableRenderRequestBody": false,
      "settingEncodeUrl": true,
      "settingRebuildPath": true,
      "settingFollowRedirects": "global",
      "_type": "request"
    },
    {
      "_id": "req_45d7fa5a29e24ff1be4d5b3b60240e0d",
      "parentId": "fld_2f31ff0280054015b4fe74dd049b6129",
      "modified": 1728067658509,
      "created": 1728067658509,
      "url": "http://localhost:3000/products/",
      "name": "all products",
      "description": "",
      "method": "GET",
      "body": {},
      "parameters": [
        {
          "id": "pair_1aa222606f4244c89bf79f4346ff7e64",
          "name": "orderBy",
          "value": "id",
          "description": ""
        }
      ],
      "headers": [{ "name": "User-Agent", "value": "insomnia/2023.5.8" }],
      "authentication": {},
      "metaSortKey": -1727374149432,
      "isPrivate": false,
      "settingStoreCookies": true,
      "settingSendCookies": true,
      "settingDisableRenderRequestBody": false,
      "settingEncodeUrl": true,
      "settingRebuildPath": true,
      "settingFollowRedirects": "global",
      "_type": "request"
    },
    {
      "_id": "fld_2f31ff0280054015b4fe74dd049b6129",
      "parentId": "wrk_4b01b1ef345b4e99b769c016507fff36",
      "modified": 1728067658500,
      "created": 1728067658500,
      "name": "REPORTS",
      "description": "",
      "environment": {},
      "environmentPropertyOrder": null,
      "metaSortKey": -1725333482366.0781,
      "_type": "request_group"
    },
    {
      "_id": "req_fd697b5072464788962665a0f00771a4",
      "parentId": "fld_2f31ff0280054015b4fe74dd049b6129",
      "modified": 1728067658529,
      "created": 1728067658529,
      "url": "http://localhost:3000/products/3",
      "name": "product by id",
      "description": "",
      "method": "GET",
      "body": {},
      "parameters": [],
      "headers": [{ "name": "User-Agent", "value": "insomnia/2023.5.8" }],
      "authentication": {},
      "metaSortKey": -1727374149382,
      "isPrivate": false,
      "settingStoreCookies": true,
      "settingSendCookies": true,
      "settingDisableRenderRequestBody": false,
      "settingEncodeUrl": true,
      "settingRebuildPath": true,
      "settingFollowRedirects": "global",
      "_type": "request"
    },
    {
      "_id": "req_c31bdabc77694bc185e0e7a9f71691bb",
      "parentId": "fld_2f31ff0280054015b4fe74dd049b6129",
      "modified": 1728067658535,
      "created": 1728067658535,
      "url": "http://localhost:3000/products/2",
      "name": "delete product by id",
      "description": "",
      "method": "DELETE",
      "body": {},
      "parameters": [],
      "headers": [{ "name": "User-Agent", "value": "insomnia/2023.5.8" }],
      "authentication": {},
      "metaSortKey": -1727374149332,
      "isPrivate": false,
      "settingStoreCookies": true,
      "settingSendCookies": true,
      "settingDisableRenderRequestBody": false,
      "settingEncodeUrl": true,
      "settingRebuildPath": true,
      "settingFollowRedirects": "global",
      "_type": "request"
    },
    {
      "_id": "req_1932d48ebf3b4215b18a506cfffffbe6",
      "parentId": "fld_2f31ff0280054015b4fe74dd049b6129",
      "modified": 1728067658547,
      "created": 1728067658547,
      "url": "http://localhost:3000/products/activate/4",
      "name": "reactivate product by id",
      "description": "",
      "method": "POST",
      "body": {},
      "parameters": [],
      "headers": [{ "name": "User-Agent", "value": "insomnia/2023.5.8" }],
      "authentication": {},
      "metaSortKey": -1727374149282,
      "isPrivate": false,
      "settingStoreCookies": true,
      "settingSendCookies": true,
      "settingDisableRenderRequestBody": false,
      "settingEncodeUrl": true,
      "settingRebuildPath": true,
      "settingFollowRedirects": "global",
      "_type": "request"
    },
    {
      "_id": "req_8c5c9b2827db49249eef2de268e41dd7",
      "parentId": "fld_2f31ff0280054015b4fe74dd049b6129",
      "modified": 1728067658503,
      "created": 1728067658503,
      "url": "http://localhost:3000/products/200",
      "name": "update product",
      "description": "",
      "method": "PATCH",
      "body": { "mimeType": "application/json", "text": "" },
      "parameters": [
        {
          "id": "pair_4efb578c6a3c439dad6d7753294bedde",
          "name": "origin",
          "value": "MADE",
          "description": "",
          "disabled": false
        },
        {
          "id": "pair_563ba9931c6e49fa9bad00603d41f28f",
          "name": "category_id",
          "value": "1",
          "description": "",
          "disabled": false
        },
        {
          "id": "pair_5380b02a4fbe46088a91d9fe5c54bd96",
          "name": "group_id",
          "value": "1",
          "description": "",
          "disabled": false
        },
        {
          "id": "pair_8ed01a5930a2467bae6080c496e84518",
          "name": "supplier_id",
          "value": "1",
          "description": "",
          "disabled": false
        },
        {
          "id": "pair_a7fa6ba98ff6419e9dad8655124feb51",
          "name": "nutritional_info",
          "value": "macaco",
          "description": "",
          "disabled": false
        },
        {
          "id": "pair_2b0c0be95b9746fe85515bcd96c9d726",
          "name": "description",
          "value": "macaco",
          "description": ""
        }
      ],
      "headers": [
        { "name": "Content-Type", "value": "application/json" },
        { "name": "User-Agent", "value": "insomnia/2023.5.8" }
      ],
      "authentication": {},
      "metaSortKey": -1727374149232,
      "isPrivate": false,
      "settingStoreCookies": true,
      "settingSendCookies": true,
      "settingDisableRenderRequestBody": false,
      "settingEncodeUrl": true,
      "settingRebuildPath": true,
      "settingFollowRedirects": "global",
      "_type": "request"
    },
    {
      "_id": "req_9aed4a76a8f94b1c817fd007c9d3f2ca",
      "parentId": "fld_2f31ff0280054015b4fe74dd049b6129",
      "modified": 1728067658558,
      "created": 1728067658558,
      "url": "http://localhost:3000/products/bulk-remove",
      "name": "bulk remove products",
      "description": "",
      "method": "DELETE",
      "body": {
        "mimeType": "application/json",
        "text": "{\n  \"ids\": [1, 2, 3, 4, 5]\n}"
      },
      "parameters": [],
      "headers": [
        { "name": "Content-Type", "value": "application/json" },
        { "name": "User-Agent", "value": "insomnia/2023.5.8" }
      ],
      "authentication": {},
      "metaSortKey": -1727374147767.625,
      "isPrivate": false,
      "settingStoreCookies": true,
      "settingSendCookies": true,
      "settingDisableRenderRequestBody": false,
      "settingEncodeUrl": true,
      "settingRebuildPath": true,
      "settingFollowRedirects": "global",
      "_type": "request"
    },
    {
      "_id": "req_ea2a7c1d1eb74db3806dc5858c47a4d4",
      "parentId": "fld_2f31ff0280054015b4fe74dd049b6129",
      "modified": 1728067658564,
      "created": 1728067658564,
      "url": "http://localhost:3000/products/bulk-update",
      "name": "bulk update product",
      "description": "",
      "method": "PATCH",
      "body": {
        "mimeType": "application/json",
        "text": "\t{\n\t\"id\": 8,\n\t\"description\": \"abacaxi\",\n\t\"origin\": \"MADE\",\n\t\"category_id\": 3,\n\t\"group_id\": 3,\n\t\"supplier_id\": 3,\n\t\"nutritional_info\": \"abacaxi\"\n\t}\n\n\t{\n\t\"id\": 9,\n\t\"description\": \"BERGAMOTA\",\n\t\"origin\": \"MADE\",\n\t\"category_id\": 2,\n\t\"group_id\": 2,\n\t\"supplier_id\": 2,\n\t\"nutritional_info\": \"BERGAMOTA\"\n\t}"
      },
      "parameters": [],
      "headers": [
        { "name": "Content-Type", "value": "application/json" },
        { "name": "User-Agent", "value": "insomnia/2023.5.8" }
      ],
      "authentication": {},
      "metaSortKey": -1727374146303.25,
      "isPrivate": false,
      "settingStoreCookies": true,
      "settingSendCookies": true,
      "settingDisableRenderRequestBody": false,
      "settingEncodeUrl": true,
      "settingRebuildPath": true,
      "settingFollowRedirects": "global",
      "_type": "request"
    },
    {
      "_id": "req_a0a31b538e054e7ba0ecb9c50e8b2901",
      "parentId": "fld_2f31ff0280054015b4fe74dd049b6129",
      "modified": 1728067658541,
      "created": 1728067658541,
      "url": "http://localhost:3000/products/",
      "name": "create product",
      "description": "",
      "method": "POST",
      "body": {
        "mimeType": "application/json",
        "text": "\t{\n\t\t\"description\": \"elefante\",\n\t\t\"code\": \"elefante\",\n\t\t\"sku\": \"elefante\",\n\t\t\"origin\": \"RAW_MATERIAL\",\n\t\t\"unit_measure\": \"UN\",\n\t\t\"category_id\": 4,\n\t\t\"group_id\": 4,\n\t\t\"supplier_id\": 4,\n\t\t\"nutritional_info\": \"elefante\"\n\t}"
      },
      "parameters": [],
      "headers": [
        { "name": "Content-Type", "value": "application/json" },
        { "name": "User-Agent", "value": "insomnia/2023.5.8" }
      ],
      "authentication": {},
      "metaSortKey": -1727374143374.5,
      "isPrivate": false,
      "settingStoreCookies": true,
      "settingSendCookies": true,
      "settingDisableRenderRequestBody": false,
      "settingEncodeUrl": true,
      "settingRebuildPath": true,
      "settingFollowRedirects": "global",
      "_type": "request"
    },
    {
      "_id": "env_aae355c348085db91e14cc4ca2e3d2f34ebabbb4",
      "parentId": "wrk_4b01b1ef345b4e99b769c016507fff36",
      "modified": 1726460010545,
      "created": 1726460010545,
      "name": "Base Environment",
      "data": {},
      "dataPropertyOrder": null,
      "color": null,
      "isPrivate": false,
      "metaSortKey": 1726460010545,
      "_type": "environment"
    },
    {
      "_id": "jar_aae355c348085db91e14cc4ca2e3d2f34ebabbb4",
      "parentId": "wrk_4b01b1ef345b4e99b769c016507fff36",
      "modified": 1726460010547,
      "created": 1726460010547,
      "name": "Default Jar",
      "cookies": [],
      "_type": "cookie_jar"
    }
  ]
}
